jds7dg28d/__init__.py
jds7dg28d-9999.99.99.dist-info/DESCRIPTION.rst
jds7dg28d-9999.99.99.dist-info/METADATA
jds7dg28d-9999.99.99.dist-info/RECORD
jds7dg28d-9999.99.99.dist-info/WHEEL
jds7dg28d-9999.99.99.dist-info/metadata.json
jds7dg28d-9999.99.99.dist-info/top_level.txt
