Metadata-Version: 2.0
Name: jds7dg28d
Version: 9999.99.99
Summary: jds7dg28d
Home-page: UNKNOWN
Author: jds7dg28d
Author-email: jds7dg28d@gmail.com
License: UNKNOWN
Platform: UNKNOWN
Classifier: Programming Language :: Python :: 3
Classifier: Programming Language :: Python :: 2
